fundamentus/__init__.py
fundamentus/detalhes.py
fundamentus/logging.py
fundamentus/papel.py
fundamentus/resultado.py
fundamentus/setor.py
fundamentus/utils.py
fundamentus-0.3.2.dist-info/licenses/LICENSE
fundamentus-0.3.2.dist-info/METADATA
fundamentus-0.3.2.dist-info/WHEEL
fundamentus-0.3.2.dist-info/top_level.txt
fundamentus-0.3.2.dist-info/RECORD
