Metadata-Version: 2.4
Name: fundamentus
Version: 0.3.2
Summary: ('Fundamentus: API to load data from Fundamentus website: https://www.fundamentus.com.br/',)
Home-page: https://github.com/mv/fundamentus-api/
Author: Mv-Marcus Vinicius Ferreira
Author-email: ferreira.mv@gmail.com
License: MIT
Classifier: License :: OSI Approved :: MIT License
Classifier: Programming Language :: Python
Classifier: Programming Language :: Python :: 3
Classifier: Programming Language :: Python :: 3.9
Classifier: Programming Language :: Python :: 3.10
Classifier: Programming Language :: Python :: 3.11
Classifier: Programming Language :: Python :: 3.12
Classifier: Programming Language :: Python :: 3.13
Requires-Python: >=3.9
License-File: LICENSE
Requires-Dist: requests>=2.32.4
Requires-Dist: requests-cache>=1.2.1
Requires-Dist: pandas>=2.3.0
Requires-Dist: lxml>=5.4.0
Requires-Dist: tabulate>=0.9.0
Dynamic: author
Dynamic: author-email
Dynamic: classifier
Dynamic: description
Dynamic: description-content-type
Dynamic: home-page
Dynamic: license
Dynamic: license-file
Dynamic: requires-dist
Dynamic: requires-python
Dynamic: summary
